{
    "Luca": {
        "ruolo": "Indifferente",
        "vinte": 0,
        "perse": 0,
        "elo": 1200
    },
    "Giovanni": {
        "ruolo": "Indifferente",
        "vinte": 0,
        "perse": 0,
        "elo": 1201.1500225556908
    },
    "Alessandro": {
        "ruolo": "Indifferente",
        "vinte": 0,
        "perse": 0,
        "elo": 1200.0
    },
    "Lorenzo": {
        "ruolo": "Indifferente",
        "vinte": 0,
        "perse": 0,
        "elo": 1200
    },
    "Alex": {
        "ruolo": "Indifferente",
        "vinte": 0,
        "perse": 0,
        "elo": 1200
    },
    "Alexander": {
        "ruolo": "Difesa",
        "vinte": 0,
        "perse": 0,
        "elo": 1238.8499774443092
    },
    "Rafael": {
        "ruolo": "Indifferente",
        "vinte": 0,
        "perse": 0,
        "elo": 1200
    },
    "Chiara": {
        "ruolo": "Indifferente",
        "vinte": 0,
        "perse": 0,
        "elo": 1160.0
    },
    "Ludovica": {
        "ruolo": "Indifferente",
        "vinte": 0,
        "perse": 0,
        "elo": 1200
    },
    "Lucio": {
        "ruolo": "Indifferente",
        "vinte": 0,
        "perse": 0,
        "elo": 1238.8499774443092
    },
    "Libero": {
        "ruolo": "Indifferente",
        "vinte": 0,
        "perse": 0,
        "elo": 1200
    },
    "Alberto": {
        "ruolo": "Attaccante",
        "vinte": 0,
        "perse": 0,
        "elo": 1161.1500225556908
    },
    "Salvatore": {
        "ruolo": "Indifferente",
        "vinte": 0,
        "perse": 0,
        "elo": 1200
    }
}